[
    {
        "id": 0,
        "text": "Этот парень проходил обучение веб-разработке не где-то, а в Loftschool! 4,5 месяца только самых тяжелых испытаний и бессонных ночей!",
        "name": "Ковальчук Дмитрий",
        "occ": "Основатель Loftschool",
        "pic": "dmitriy.png"
    },
    {
        "id": 1,
        "text": "Этот код выдержит любые испытания. Только пожалуйста, не загружайте сайт на слишком старых браузерах",
        "name": "Владимир Сабанцев",
        "occ": "Преподаватель",
        "pic": "vladimir.png"
    },
    {
        "id": 2,
        "text": "Этот парень проходил обучение веб-разработке не где-то, а в Loftschool! 4,5 месяца только самых тяжелых испытаний и бессонных ночей!",
        "name": "Ковальчук Дмитрий",
        "occ": "Основатель Loftschool",
        "pic": "dmitriy.png"
    },
    {
        "id": 3,
        "text": "Этот код выдержит любые испытания. Только пожалуйста, не загружайте сайт на слишком старых браузерах",
        "name": "Владимир Сабанцев",
        "occ": "Преподаватель",
        "pic": "vladimir.png"
    }
]